sys_design_diagram/__init__.py
sys_design_diagram/_version.py
sys_design_diagram/cli.py
sys_design_diagram/diagrams.py
sys_design_diagram/exceptions.py
sys_design_diagram/interfaces.py
sys_design_diagram/log.py
sys_design_diagram/mermaid.py
sys_design_diagram/messages.py
sys_design_diagram/plantuml.py
sys_design_diagram/process_diagrams.py
sys_design_diagram/utils.py
sys_design_diagram-2.0.2.dist-info/METADATA
sys_design_diagram-2.0.2.dist-info/WHEEL
sys_design_diagram-2.0.2.dist-info/entry_points.txt
sys_design_diagram-2.0.2.dist-info/licenses/LICENSE
sys_design_diagram-2.0.2.dist-info/RECORD
