Metadata-Version: 2.4
Name: sys-design-diagram
Version: 2.0.2
Summary: A package for generating architecture diagrams using PlantUML, diagrams, and Mermaid.
Author-email: Aydin Abdi <ayd.abd@gmail.com>
License-Expression: MIT
License-File: LICENSE
Keywords: architecture,design,diagrams,mermaid,plantuml,system,uml
Classifier: Development Status :: 5 - Production/Stable
Classifier: Intended Audience :: Developers
Classifier: License :: OSI Approved :: MIT License
Classifier: Operating System :: OS Independent
Classifier: Programming Language :: Python :: 3
Classifier: Topic :: Software Development :: Documentation
Classifier: Topic :: Software Development :: Libraries :: Python Modules
Classifier: Typing :: Typed
Requires-Python: >=3.9
Requires-Dist: click
Requires-Dist: diagrams
Requires-Dist: loguru
